billable/__init__.py
billable/admin.py
billable/api.py
billable/apps.py
billable/models.py
billable/schemas.py
billable/signals.py
billable/migrations/0001_initial.py
billable/migrations/__init__.py
billable/services/__init__.py
billable/services/order_service.py
billable/services/product_service.py
billable/services/quota_service.py
billable/services/user_product_service.py
billable/tests/test_api.py
billable/tests/test_services.py
billable/tests/test_settings.py
billable-0.1.0.dist-info/METADATA
billable-0.1.0.dist-info/WHEEL
billable-0.1.0.dist-info/top_level.txt
billable-0.1.0.dist-info/RECORD
