Metadata-Version: 2.4
Name: billable
Version: 0.1.0
Summary: Universal Billing Engine
Requires-Python: >=3.10
Requires-Dist: Django>=4.2
Requires-Dist: django-ninja>=1.0
